odoo/addons/shopinvader_api_address/README.rst
odoo/addons/shopinvader_api_address/__init__.py
odoo/addons/shopinvader_api_address/__manifest__.py
odoo/addons/shopinvader_api_address/schemas.py
odoo/addons/shopinvader_api_address/i18n/shopinvader_api_address.pot
odoo/addons/shopinvader_api_address/readme/CONTRIBUTORS.rst
odoo/addons/shopinvader_api_address/readme/DESCRIPTION.rst
odoo/addons/shopinvader_api_address/routers/__init__.py
odoo/addons/shopinvader_api_address/routers/address_service.py
odoo/addons/shopinvader_api_address/security/res_groups.xml
odoo/addons/shopinvader_api_address/security/res_partner.xml
odoo/addons/shopinvader_api_address/static/description/icon.png
odoo/addons/shopinvader_api_address/static/description/index.html
odoo/addons/shopinvader_api_address/tests/__init__.py
odoo/addons/shopinvader_api_address/tests/test_shopinvader_address_api.py
odoo_addon_shopinvader_api_address-16.0.1.3.3.dist-info/METADATA
odoo_addon_shopinvader_api_address-16.0.1.3.3.dist-info/WHEEL
odoo_addon_shopinvader_api_address-16.0.1.3.3.dist-info/top_level.txt
odoo_addon_shopinvader_api_address-16.0.1.3.3.dist-info/RECORD
